tests/__init__.py
tests/_test_datamodules.py
tests/_test_datasets.py
tests/test_transforms.py
tests/models/__init__.py
tests/models/test_rams.py
torchrs/__init__.py
torchrs/transforms.py
torchrs/datasets/__init__.py
torchrs/datasets/advance.py
torchrs/datasets/aid.py
torchrs/datasets/brazilian_coffee.py
torchrs/datasets/dubai_segmentation.py
torchrs/datasets/etci2021.py
torchrs/datasets/eurosat.py
torchrs/datasets/fair1m.py
torchrs/datasets/gid15.py
torchrs/datasets/hkh_glacier.py
torchrs/datasets/hrscd.py
torchrs/datasets/inria_ail.py
torchrs/datasets/levircd.py
torchrs/datasets/oscd.py
torchrs/datasets/patternnet.py
torchrs/datasets/probav.py
torchrs/datasets/resisc45.py
torchrs/datasets/rsicd.py
torchrs/datasets/rsscn7.py
torchrs/datasets/rsvqa.py
torchrs/datasets/s2looking.py
torchrs/datasets/s2mtcp.py
torchrs/datasets/sat.py
torchrs/datasets/sydney_captions.py
torchrs/datasets/tiselac.py
torchrs/datasets/ucm.py
torchrs/datasets/ucm_captions.py
torchrs/datasets/utils.py
torchrs/datasets/whu_rs19.py
torchrs/datasets/zuericrop.py
torchrs/models/__init__.py
torchrs/models/fc_cd.py
torchrs/models/oscd.py
torchrs/models/rams.py
torchrs/train/__init__.py
torchrs/train/datamodules/__init__.py
torchrs/train/datamodules/advance.py
torchrs/train/datamodules/aid.py
torchrs/train/datamodules/base.py
torchrs/train/datamodules/brazilian_coffee.py
torchrs/train/datamodules/dubai_segmentation.py
torchrs/train/datamodules/etci2021.py
torchrs/train/datamodules/eurosat.py
torchrs/train/datamodules/fair1m.py
torchrs/train/datamodules/gid15.py
torchrs/train/datamodules/hkh_glacier.py
torchrs/train/datamodules/hrscd.py
torchrs/train/datamodules/inria_ail.py
torchrs/train/datamodules/levircd.py
torchrs/train/datamodules/oscd.py
torchrs/train/datamodules/patternnet.py
torchrs/train/datamodules/probav.py
torchrs/train/datamodules/resisc45.py
torchrs/train/datamodules/rsicd.py
torchrs/train/datamodules/rsscn7.py
torchrs/train/datamodules/rsvqa.py
torchrs/train/datamodules/s2looking.py
torch_rs-0.0.4.dist-info/LICENSE
torch_rs-0.0.4.dist-info/METADATA
torch_rs-0.0.4.dist-info/WHEEL
torch_rs-0.0.4.dist-info/top_level.txt
torch_rs-0.0.4.dist-info/RECORD
