Metadata-Version: 2.1
Name: torch-rs
Version: 0.0.4
Summary: PyTorch Library for Remote Sensing
Home-page: https://github.com/isaaccorley/torchrs
Author: Isaac Corley
Author-email: isaac.corley@my.utsa.edu
License: MIT License
Download-URL: https://github.com/isaaccorley/torchrs/archive/0.0.4.tar.gz
Project-URL: Bug Tracker, https://github.com/isaaccorley/torchrs/issues
Keywords: pytorch,remote-sensing,computer-vision
Platform: UNKNOWN
Classifier: Programming Language :: Python :: 3
Classifier: License :: OSI Approved :: MIT License
Classifier: Operating System :: OS Independent
Requires-Python: >=3.7
License-File: LICENSE
Requires-Dist: torch (>=1.9.0)
Requires-Dist: torchvision (>=0.10.0)
Requires-Dist: torchaudio (>=0.9.0)
Requires-Dist: einops (>=0.3.0)
Requires-Dist: numpy (>=1.21.0)
Requires-Dist: pillow (>=8.3.1)
Requires-Dist: tifffile (>=2021.7.2)
Requires-Dist: h5py (>=3.3.0)
Requires-Dist: imagecodecs (>=2021.7.30)
Provides-Extra: train
Requires-Dist: pytorch-lightning (>=1.4.0) ; extra == 'train'
Requires-Dist: torchmetrics (>=0.4.1) ; extra == 'train'
